setup.py
sb_modules/__init__.py
sb_modules/constants.py
sb_modules/sb_log.py
sb_modules/sb_settings.py
sb_modules/sb_utils.py
sb_modules.egg-info/PKG-INFO
sb_modules.egg-info/SOURCES.txt
sb_modules.egg-info/dependency_links.txt
sb_modules.egg-info/not-zip-safe
sb_modules.egg-info/top_level.txt