Metadata-Version: 1.0
Name: sb-modules
Version: 0.1
Summary: Simple helpers
Home-page: http://github.com/cidrblock/sb_helpers
Author: Bradley A. Thornton
Author-email: brad@thethorntons.net
License: MIT
Platform: UNKNOWN
